adaptive_core_ext.cpython-313-darwin.so
include/adaptive_core/cluster.hpp
include/adaptive_core/scorer.hpp
include/adaptive_core/result.hpp
include/adaptive_core/router.hpp
include/adaptive_core/profile.hpp
include/adaptive_core/cluster_backend.hpp
include/adaptive_core/cuda/cluster_cuda.hpp
lib/libadaptive_core.a
adaptive_router_core-0.1.11.dist-info/RECORD
adaptive_router_core-0.1.11.dist-info/WHEEL
adaptive_router_core-0.1.11.dist-info/METADATA
