Metadata-Version: 2.1
Name: adaptive-router-core
Version: 0.1.11
Summary: C++ inference core for Adaptive Router
Requires-Python: <4.0,>=3.11
